{
  "id": "",
  "name": "",
  "font_family": "iconfont",
  "css_prefix_text": "icon-",
  "description": "",
  "glyphs": [
    {
      "icon_id": "218135",
      "name": "淘公仔",
      "font_class": "taogongzi",
      "unicode": "e605",
      "unicode_decimal": 58885
    },
    {
      "icon_id": "364535",
      "name": "搜索－放大镜",
      "font_class": "sousuofangdajing",
      "unicode": "e624",
      "unicode_decimal": 58916
    },
    {
      "icon_id": "473419",
      "name": "箭头",
      "font_class": "1212",
      "unicode": "e613",
      "unicode_decimal": 58899
    },
    {
      "icon_id": "575359",
      "name": "箭头",
      "font_class": "jiantouyou",
      "unicode": "e60c",
      "unicode_decimal": 58892
    },
    {
      "icon_id": "2008045",
      "name": "菜单",
      "font_class": "menuUp",
      "unicode": "e6f3",
      "unicode_decimal": 59123
    },
    {
      "icon_id": "2173653",
      "name": "箭头",
      "font_class": "arrow-left-copy",
      "unicode": "e505",
      "unicode_decimal": 58629
    },
    {
      "icon_id": "2795812",
      "name": "照片 拍照",
      "font_class": "zhaopianpaizhao",
      "unicode": "e653",
      "unicode_decimal": 58963
    },
    {
      "icon_id": "4667328",
      "name": "笑脸",
      "font_class": "smile",
      "unicode": "e61b",
      "unicode_decimal": 58907
    },
    {
      "icon_id": "5373211",
      "name": "下箭头",
      "font_class": "arrow-left",
      "unicode": "e54a",
      "unicode_decimal": 58698
    },
    {
      "icon_id": "6080422",
      "name": "购物车",
      "font_class": "gouwuche1",
      "unicode": "e50d",
      "unicode_decimal": 58637
    },
    {
      "icon_id": "6542010",
      "name": "关  闭",
      "font_class": "guanbi",
      "unicode": "e6a1",
      "unicode_decimal": 59041
    },
    {
      "icon_id": "8605211",
      "name": "引号",
      "font_class": "zhonghongiconbuchong-24-copy",
      "unicode": "e729",
      "unicode_decimal": 59177
    },
    {
      "icon_id": "9626788",
      "name": "实心星星",
      "font_class": "start",
      "unicode": "e502",
      "unicode_decimal": 58626
    },
    {
      "icon_id": "9669061",
      "name": "二维码",
      "font_class": "ico",
      "unicode": "e501",
      "unicode_decimal": 58625
    }
  ]
}
